jupyter_www_proxy/__init__.py
jupyter_www_proxy/icons/www.dio
jupyter_www_proxy/icons/www.svg
jupyter_www_proxy-0.1.2.dist-info/LICENSE
jupyter_www_proxy-0.1.2.dist-info/METADATA
jupyter_www_proxy-0.1.2.dist-info/WHEEL
jupyter_www_proxy-0.1.2.dist-info/entry_points.txt
jupyter_www_proxy-0.1.2.dist-info/top_level.txt
jupyter_www_proxy-0.1.2.dist-info/RECORD
